docs/Makefile
docs/advanced_usage.rst
docs/changelog.rst
docs/conf.py
docs/index.rst
docs/installation.rst
docs/intro.rst
docs/make.bat
docs/reference_api.rst
docs/usage.rst
docs/img/gui.png
docs/img/gui_region_language.png
nxbrew_dl/__init__.py
nxbrew_dl/configs/general.yml
nxbrew_dl/configs/regex.yml
nxbrew_dl/gui/__init__.py
nxbrew_dl/gui/custom_widgets.py
nxbrew_dl/gui/gui_about.py
nxbrew_dl/gui/gui_nxbrew_dl.py
nxbrew_dl/gui/gui_regions_languages.py
nxbrew_dl/gui/gui_utils.py
nxbrew_dl/gui/layout_about.py
nxbrew_dl/gui/layout_about.ui
nxbrew_dl/gui/layout_nxbrew_dl.py
nxbrew_dl/gui/layout_nxbrew_dl.ui
nxbrew_dl/gui/layout_regions_languages.py
nxbrew_dl/gui/layout_regions_languages.ui
nxbrew_dl/gui/img/logo.ico
nxbrew_dl/gui/img/logo.svg
nxbrew_dl/nxbrew_dl/__init__.py
nxbrew_dl/nxbrew_dl/nxbrew.py
nxbrew_dl/util/__init__.py
nxbrew_dl/util/discord_tools.py
nxbrew_dl/util/download_tools.py
nxbrew_dl/util/github_tools.py
nxbrew_dl/util/html_tools.py
nxbrew_dl/util/io_tools.py
nxbrew_dl/util/log_utils.py
nxbrew_dl/util/regex_tools.py
nxbrew_dl-0.7.3.dist-info/licenses/LICENSE
nxbrew_dl-0.7.3.dist-info/METADATA
nxbrew_dl-0.7.3.dist-info/WHEEL
nxbrew_dl-0.7.3.dist-info/entry_points.txt
nxbrew_dl-0.7.3.dist-info/top_level.txt
nxbrew_dl-0.7.3.dist-info/RECORD
