Metadata-Version: 2.4
Name: nxbrew_dl
Version: 0.7.3
Summary: NXBrew Downloader
Author: bbtufty
Maintainer: bbtufty
License:                     GNU GENERAL PUBLIC LICENSE
Project-URL: Homepage, https://github.com/bbtufty/nxbrew-dl
Project-URL: Bug Reports, https://github.com/bbtufty/nxbrew-dl/issues
Project-URL: Source, https://github.com/bbtufty/nxbrew-dl
Classifier: Development Status :: 3 - Alpha
Classifier: License :: OSI Approved :: GNU General Public License v3 or later (GPLv3+)
Classifier: Programming Language :: Python
Classifier: Programming Language :: Python :: 3
Classifier: Programming Language :: Python :: 3.11
Classifier: Programming Language :: Python :: 3.12
Classifier: Programming Language :: Python :: 3 :: Only
Requires-Python: >=3.11
License-File: LICENSE
Requires-Dist: beautifulsoup4==4.14.2
Requires-Dist: colorlog==6.10.1
Requires-Dist: curl_cffi==0.13.0
Requires-Dist: discordwebhook==1.0.3
Requires-Dist: logredactor==0.0.2
Requires-Dist: lxml==6.0.2
Requires-Dist: myjdapi==1.1.10
Requires-Dist: numpy==2.3.4
Requires-Dist: pathvalidate==3.3.1
Requires-Dist: PySide6==6.10.0
Requires-Dist: requests==2.32.5
Requires-Dist: PyYAML==6.0.3
Provides-Extra: docs
Requires-Dist: sphinx==8.2.3; extra == "docs"
Requires-Dist: sphinx-automodapi==0.20.0; extra == "docs"
Requires-Dist: sphinx-rtd-theme==3.0.2; extra == "docs"
Dynamic: license-file
